<?xml version="1.0" encoding="UTF-8" standalone="yes"?>
<TrafficMatrixFile xmlns:xsi="http://www.w3.org/2001/XMLSchema-instance" xsi:noNamespaceSchemaLocation="http://totem.run.montefiore.ulg.ac.be/Schema/TrafficMatrix-v1_2.xsd">
  <info>
    <title>Intradomain traffic matrix generated by geant-TM-all.pl</title>
    <date>2005-03-21T03:00:00</date>
    <duration>900</duration>
    <author>Steve Uhlig</author>
    <units>
        <unit type="bandwidth" value="kbps"/>
    </units>
  </info>
  <IntraTM ASID="20965">
    <src id="12">
      <dst id="12">308631.2533</dst>
      <dst id="13">52105.1289</dst>
      <dst id="19">12733.6533</dst>
      <dst id="23">5132.8533</dst>
      <dst id="8">1628.3644</dst>
      <dst id="18">151913.1733</dst>
      <dst id="4">3814.8356</dst>
      <dst id="1">24709.0222</dst>
      <dst id="5">8345.8756</dst>
      <dst id="3">100.4267</dst>
      <dst id="10">3108.6933</dst>
      <dst id="22">4529.1289</dst>
      <dst id="7">9603.8933</dst>
      <dst id="2">31817.4844</dst>
      <dst id="6">21301.4400</dst>
      <dst id="16">2725.1911</dst>
      <dst id="14">524.1778</dst>
      <dst id="20">778.1600</dst>
      <dst id="11">18.2933</dst>
      <dst id="9">4677.9111</dst>
      <dst id="17">59396.9067</dst>
      <dst id="21">5301.3689</dst>
      <dst id="15">918.4533</dst>
    </src>
    <src id="13">
      <dst id="12">11882.3289</dst>
      <dst id="13">135.5556</dst>
      <dst id="19">7941.3067</dst>
      <dst id="23">10580.6044</dst>
      <dst id="8">368.8089</dst>
      <dst id="18">18097.6978</dst>
      <dst id="4">7.3867</dst>
      <dst id="1">1517.2800</dst>
      <dst id="5">495.7956</dst>
      <dst id="3">186.7644</dst>
      <dst id="10">2.3111</dst>
      <dst id="22">9872.8889</dst>
      <dst id="7">3975.1200</dst>
      <dst id="2">36154.6756</dst>
      <dst id="6">71.2622</dst>
      <dst id="16">10756.8711</dst>
      <dst id="14">115.6089</dst>
      <dst id="20">712.7111</dst>
      <dst id="11">156.0089</dst>
      <dst id="9">2630.1156</dst>
      <dst id="17">11758.2311</dst>
      <dst id="21">2635.9733</dst>
      <dst id="15">6093.4489</dst>
    </src>
    <src id="19">
      <dst id="12">34555.0756</dst>
      <dst id="13">1626.3022</dst>
      <dst id="23">100.5867</dst>
      <dst id="8">0.3556</dst>
      <dst id="18">16.2844</dst>
      <dst id="4">148.2400</dst>
      <dst id="1">248.7022</dst>
      <dst id="5">15.5467</dst>
      <dst id="3">15.5644</dst>
      <dst id="10">94.9067</dst>
      <dst id="22">51.4489</dst>
      <dst id="7">3659.3689</dst>
      <dst id="2">1748.4533</dst>
      <dst id="6">14.8178</dst>
      <dst id="16">1959.2267</dst>
      <dst id="14">106.5600</dst>
      <dst id="20">69.6533</dst>
      <dst id="11">26.6667</dst>
      <dst id="9">22.5422</dst>
      <dst id="17">10539.5822</dst>
      <dst id="21">800.9333</dst>
      <dst id="15">1.7778</dst>
    </src>
    <src id="23">
      <dst id="12">5828.8889</dst>
      <dst id="13">698.4889</dst>
      <dst id="19">14.8978</dst>
      <dst id="8">73.7067</dst>
      <dst id="18">5705.4578</dst>
      <dst id="4">92.3556</dst>
      <dst id="1">55.2889</dst>
      <dst id="3">4.5867</dst>
      <dst id="10">303.0311</dst>
      <dst id="22">21.9911</dst>
      <dst id="7">1610.8178</dst>
      <dst id="2">171.1378</dst>
      <dst id="16">9.9911</dst>
      <dst id="11">13.0489</dst>
      <dst id="9">71.4044</dst>
      <dst id="17">1386.0089</dst>
      <dst id="21">678.0000</dst>
      <dst id="15">13.3333</dst>
    </src>
    <src id="8">
      <dst id="12">6037.8667</dst>
      <dst id="13">338.4178</dst>
      <dst id="19">3.6889</dst>
      <dst id="23">4405.7956</dst>
      <dst id="18">44.8000</dst>
      <dst id="4">238.7111</dst>
      <dst id="1">1649.1289</dst>
      <dst id="5">395.8667</dst>
      <dst id="3">0.4356</dst>
      <dst id="10">58.2133</dst>
      <dst id="7">58.0978</dst>
      <dst id="2">169.7511</dst>
      <dst id="6">51.8756</dst>
      <dst id="16">216924.0622</dst>
      <dst id="9">77591.8133</dst>
      <dst id="17">32695.7778</dst>
      <dst id="21">29.8044</dst>
      <dst id="15">0.4622</dst>
    </src>
    <src id="18">
      <dst id="12">150482.8533</dst>
      <dst id="13">504.8533</dst>
      <dst id="19">117.6889</dst>
      <dst id="23">120.9956</dst>
      <dst id="8">32.9156</dst>
      <dst id="4">61.2089</dst>
      <dst id="1">1151.4400</dst>
      <dst id="5">213.4489</dst>
      <dst id="3">3757.6711</dst>
      <dst id="10">17.5822</dst>
      <dst id="22">418.6133</dst>
      <dst id="7">213.6267</dst>
      <dst id="2">12621.9022</dst>
      <dst id="16">481.3422</dst>
      <dst id="20">36.5156</dst>
      <dst id="11">2.4711</dst>
      <dst id="9">527.3511</dst>
      <dst id="17">6917.9111</dst>
      <dst id="21">1232.5511</dst>
      <dst id="15">7.2533</dst>
    </src>
    <src id="4">
      <dst id="12">38136.2222</dst>
      <dst id="13">18.1333</dst>
      <dst id="19">3847.6000</dst>
      <dst id="23">3722.4711</dst>
      <dst id="8">1720.0711</dst>
      <dst id="18">6690.9956</dst>
      <dst id="4">37.3867</dst>
      <dst id="1">187576.3733</dst>
      <dst id="5">3931.0844</dst>
      <dst id="3">231.7956</dst>
      <dst id="22">180.3289</dst>
      <dst id="7">502.7111</dst>
      <dst id="2">137833.3067</dst>
      <dst id="6">267.9378</dst>
      <dst id="16">61721.1556</dst>
      <dst id="14">6120.1956</dst>
      <dst id="11">1412.6311</dst>
      <dst id="9">24263.1822</dst>
      <dst id="17">67693.3778</dst>
      <dst id="21">9299.7689</dst>
      <dst id="15">2186.4178</dst>
    </src>
    <src id="1">
      <dst id="12">350340.9778</dst>
      <dst id="13">3419.2000</dst>
      <dst id="19">204.8178</dst>
      <dst id="23">52.7200</dst>
      <dst id="8">66.2578</dst>
      <dst id="18">12593.1378</dst>
      <dst id="4">638.3022</dst>
      <dst id="1">746935.2000</dst>
      <dst id="5">369.5200</dst>
      <dst id="3">81.6622</dst>
      <dst id="10">3132.8089</dst>
      <dst id="7">30499.3778</dst>
      <dst id="2">115858.4800</dst>
      <dst id="6">3.9644</dst>
      <dst id="16">565616.8889</dst>
      <dst id="14">187.3156</dst>
      <dst id="20">816.5333</dst>
      <dst id="11">471.0667</dst>
      <dst id="9">1489.2800</dst>
      <dst id="17">892827.1911</dst>
      <dst id="21">598100.7111</dst>
      <dst id="15">1098.0800</dst>
    </src>
    <src id="5">
      <dst id="12">13779.2000</dst>
      <dst id="13">1645.0311</dst>
      <dst id="19">56.2578</dst>
      <dst id="8">252.0178</dst>
      <dst id="18">391.0489</dst>
      <dst id="4">273.0044</dst>
      <dst id="1">3334.9956</dst>
      <dst id="3">1.1289</dst>
      <dst id="10">801.7600</dst>
      <dst id="22">285.4400</dst>
      <dst id="7">173.2800</dst>
      <dst id="2">9759.9289</dst>
      <dst id="6">11.2444</dst>
      <dst id="16">307813.6267</dst>
      <dst id="14">28.6044</dst>
      <dst id="11">26.0622</dst>
      <dst id="9">55710.4711</dst>
      <dst id="17">39980.3822</dst>
      <dst id="21">2.4267</dst>
      <dst id="15">49.4222</dst>
    </src>
    <src id="3">
      <dst id="12">1696.1156</dst>
      <dst id="13">30442.5244</dst>
      <dst id="19">2175.7422</dst>
      <dst id="23">74.8800</dst>
      <dst id="8">41.4578</dst>
      <dst id="18">818.8356</dst>
      <dst id="4">618.9244</dst>
      <dst id="1">9085.2444</dst>
      <dst id="5">217.9289</dst>
      <dst id="3">213.4844</dst>
      <dst id="10">246.0978</dst>
      <dst id="7">2269.3778</dst>
      <dst id="2">4116.7022</dst>
      <dst id="6">3.6089</dst>
      <dst id="16">14032.2756</dst>
      <dst id="14">387.7778</dst>
      <dst id="20">68.4444</dst>
      <dst id="11">144.2133</dst>
      <dst id="9">417.9556</dst>
      <dst id="17">50601.2889</dst>
      <dst id="21">6086.9778</dst>
      <dst id="15">4.9956</dst>
    </src>
    <src id="10">
      <dst id="12">19162.0889</dst>
      <dst id="13">1091.3244</dst>
      <dst id="19">357.9822</dst>
      <dst id="23">290.8711</dst>
      <dst id="8">62.7822</dst>
      <dst id="18">6617.9556</dst>
      <dst id="1">4944.4800</dst>
      <dst id="5">1596.2044</dst>
      <dst id="3">7992.0622</dst>
      <dst id="22">93.3333</dst>
      <dst id="7">1993.5289</dst>
      <dst id="2">17296.9600</dst>
      <dst id="6">2.0711</dst>
      <dst id="16">42765.8756</dst>
      <dst id="14">2034.6933</dst>
      <dst id="20">754.0000</dst>
      <dst id="11">15.1822</dst>
      <dst id="9">7899.5644</dst>
      <dst id="17">58002.9422</dst>
      <dst id="21">3690.4711</dst>
      <dst id="15">61.8756</dst>
    </src>
    <src id="22">
      <dst id="12">5469.3511</dst>
      <dst id="13">10713.1911</dst>
      <dst id="19">79.1644</dst>
      <dst id="23">10.0889</dst>
      <dst id="8">2347.3244</dst>
      <dst id="18">1853.9644</dst>
      <dst id="4">226.3467</dst>
      <dst id="1">128.1422</dst>
      <dst id="5">771.0578</dst>
      <dst id="3">70.1867</dst>
      <dst id="10">278.0000</dst>
      <dst id="7">1381.6178</dst>
      <dst id="2">2180.5600</dst>
      <dst id="6">14.4356</dst>
      <dst id="16">871.0756</dst>
      <dst id="14">12.0978</dst>
      <dst id="11">18.1511</dst>
      <dst id="9">5315.4044</dst>
      <dst id="17">4367.2711</dst>
      <dst id="21">329.3867</dst>
    </src>
    <src id="7">
      <dst id="12">20145.2444</dst>
      <dst id="13">52289.8133</dst>
      <dst id="19">2526.7200</dst>
      <dst id="23">2594.8800</dst>
      <dst id="8">136.1067</dst>
      <dst id="18">769.7689</dst>
      <dst id="4">1279.5378</dst>
      <dst id="1">12227.0844</dst>
      <dst id="5">1974.8178</dst>
      <dst id="3">2905.9644</dst>
      <dst id="10">410.3644</dst>
      <dst id="22">895.5200</dst>
      <dst id="7">807.6800</dst>
      <dst id="2">25118.4356</dst>
      <dst id="6">0.7111</dst>
      <dst id="16">7619.5467</dst>
      <dst id="14">211.8844</dst>
      <dst id="20">269.9556</dst>
      <dst id="11">104.7200</dst>
      <dst id="9">747.2178</dst>
      <dst id="17">25690.8978</dst>
      <dst id="21">4424.2933</dst>
      <dst id="15">61.1378</dst>
    </src>
    <src id="2">
      <dst id="12">104385.3156</dst>
      <dst id="13">27573.5200</dst>
      <dst id="19">359.0756</dst>
      <dst id="23">3.3689</dst>
      <dst id="8">92.6311</dst>
      <dst id="18">86111.4133</dst>
      <dst id="4">9254.3556</dst>
      <dst id="1">10723.8667</dst>
      <dst id="5">506.4978</dst>
      <dst id="3">924.0533</dst>
      <dst id="10">2668.8178</dst>
      <dst id="22">894.0800</dst>
      <dst id="7">8923.8933</dst>
      <dst id="2">4132.0622</dst>
      <dst id="6">13687.9200</dst>
      <dst id="16">325.5911</dst>
      <dst id="14">339.3600</dst>
      <dst id="20">763.0222</dst>
      <dst id="11">202.0444</dst>
      <dst id="9">541.0844</dst>
      <dst id="17">65981.0044</dst>
      <dst id="21">7556.0889</dst>
      <dst id="15">5.0667</dst>
    </src>
    <src id="6">
      <dst id="12">217.0133</dst>
      <dst id="13">71.1911</dst>
      <dst id="19">11.4222</dst>
      <dst id="8">0.9244</dst>
      <dst id="18">0.7200</dst>
      <dst id="4">14.8622</dst>
      <dst id="1">708.7733</dst>
      <dst id="5">0.3556</dst>
      <dst id="3">40.4089</dst>
      <dst id="10">22.9333</dst>
      <dst id="22">24.2578</dst>
      <dst id="7">20.7111</dst>
      <dst id="2">1717.5022</dst>
      <dst id="16">35.5467</dst>
      <dst id="20">0.4267</dst>
      <dst id="9">12.7911</dst>
      <dst id="17">23987.7689</dst>
      <dst id="21">22.0622</dst>
    </src>
    <src id="16">
      <dst id="12">193843.7956</dst>
      <dst id="13">7213.7511</dst>
      <dst id="19">2894.7644</dst>
      <dst id="23">3.7689</dst>
      <dst id="8">114084.6933</dst>
      <dst id="18">66.2400</dst>
      <dst id="4">681.0933</dst>
      <dst id="1">5249.6178</dst>
      <dst id="5">221371.4222</dst>
      <dst id="3">9736.5511</dst>
      <dst id="10">747.4756</dst>
      <dst id="7">37.6889</dst>
      <dst id="2">3907.5022</dst>
      <dst id="6">4.0978</dst>
      <dst id="16">40589.4844</dst>
      <dst id="14">40235.3778</dst>
      <dst id="11">20720.5422</dst>
      <dst id="9">223915.3156</dst>
      <dst id="17">1979.3778</dst>
      <dst id="21">75.5556</dst>
    </src>
    <src id="14">
      <dst id="12">587.0756</dst>
      <dst id="13">2840.9244</dst>
      <dst id="19">5.1378</dst>
      <dst id="23">13.3333</dst>
      <dst id="8">35.7333</dst>
      <dst id="4">190.6489</dst>
      <dst id="1">383.3511</dst>
      <dst id="5">2.8267</dst>
      <dst id="3">585.4756</dst>
      <dst id="10">179.5556</dst>
      <dst id="7">227.6800</dst>
      <dst id="2">1681.2533</dst>
      <dst id="6">0.5244</dst>
      <dst id="16">3657.8311</dst>
      <dst id="20">0.5778</dst>
      <dst id="11">27.4667</dst>
      <dst id="9">228.7200</dst>
      <dst id="17">26594.7556</dst>
      <dst id="21">144.8889</dst>
      <dst id="15">4.2933</dst>
    </src>
    <src id="20">
      <dst id="12">712.1244</dst>
      <dst id="13">1089.7600</dst>
      <dst id="19">244.6578</dst>
      <dst id="23">2.1778</dst>
      <dst id="8">450.6044</dst>
      <dst id="18">63.5733</dst>
      <dst id="4">735.3067</dst>
      <dst id="1">118.9600</dst>
      <dst id="5">1680.3644</dst>
      <dst id="3">0.6756</dst>
      <dst id="10">192.0178</dst>
      <dst id="22">40.0000</dst>
      <dst id="7">188.8800</dst>
      <dst id="2">123.3333</dst>
      <dst id="16">4294.5244</dst>
      <dst id="20">71.2444</dst>
      <dst id="9">1429.1644</dst>
      <dst id="17">10335.1822</dst>
      <dst id="21">102.0000</dst>
    </src>
    <src id="11">
      <dst id="12">16854.8711</dst>
      <dst id="13">2506.9333</dst>
      <dst id="19">707.8044</dst>
      <dst id="23">29.3067</dst>
      <dst id="8">194.9689</dst>
      <dst id="18">223.5022</dst>
      <dst id="4">2020.9511</dst>
      <dst id="1">3920.0533</dst>
      <dst id="5">947.3778</dst>
      <dst id="3">851.1911</dst>
      <dst id="10">5202.0622</dst>
      <dst id="22">3.1467</dst>
      <dst id="7">34.9867</dst>
      <dst id="2">55344.6222</dst>
      <dst id="6">43.7333</dst>
      <dst id="16">11971.4133</dst>
      <dst id="14">80.0000</dst>
      <dst id="20">667.6089</dst>
      <dst id="11">1069.1378</dst>
      <dst id="9">4787.5556</dst>
      <dst id="17">610867.9822</dst>
      <dst id="21">463.5378</dst>
      <dst id="15">151.3511</dst>
    </src>
    <src id="9">
      <dst id="12">7837.4933</dst>
      <dst id="13">4046.7378</dst>
      <dst id="19">7.8844</dst>
      <dst id="23">248.2756</dst>
      <dst id="8">79536.8000</dst>
      <dst id="18">2.8978</dst>
      <dst id="4">1883.8844</dst>
      <dst id="1">7397.2533</dst>
      <dst id="5">1984.1511</dst>
      <dst id="3">1.2622</dst>
      <dst id="10">217.2356</dst>
      <dst id="7">887.5378</dst>
      <dst id="2">245.7867</dst>
      <dst id="6">174.4800</dst>
      <dst id="16">481046.9867</dst>
      <dst id="14">0.4622</dst>
      <dst id="11">121.7422</dst>
      <dst id="9">277929.4756</dst>
      <dst id="17">88168.2933</dst>
      <dst id="21">157.2978</dst>
      <dst id="15">395.0133</dst>
    </src>
    <src id="17">
      <dst id="12">124496.0889</dst>
      <dst id="13">23025.1822</dst>
      <dst id="19">908.9956</dst>
      <dst id="23">96.1422</dst>
      <dst id="8">258.5156</dst>
      <dst id="18">693.3600</dst>
      <dst id="4">4113.0311</dst>
      <dst id="1">13461.9911</dst>
      <dst id="5">157804.8089</dst>
      <dst id="3">5354.4533</dst>
      <dst id="10">2556.8533</dst>
      <dst id="22">2240.0000</dst>
      <dst id="7">20429.2178</dst>
      <dst id="2">10095.0133</dst>
      <dst id="6">118.7200</dst>
      <dst id="16">58361.8311</dst>
      <dst id="14">18187.2533</dst>
      <dst id="20">11848.8000</dst>
      <dst id="11">14706.1067</dst>
      <dst id="9">9133.9822</dst>
      <dst id="17">37324.4622</dst>
      <dst id="21">26730.5333</dst>
      <dst id="15">46.4178</dst>
    </src>
    <src id="21">
      <dst id="12">1859.2089</dst>
      <dst id="13">8427.5733</dst>
      <dst id="19">409.0844</dst>
      <dst id="23">24.8000</dst>
      <dst id="8">680.6400</dst>
      <dst id="18">3657.0489</dst>
      <dst id="4">2305.4133</dst>
      <dst id="1">12106.9511</dst>
      <dst id="5">236.1689</dst>
      <dst id="3">2635.2622</dst>
      <dst id="10">286.7289</dst>
      <dst id="22">0.3556</dst>
      <dst id="7">2424.1600</dst>
      <dst id="2">9523.3867</dst>
      <dst id="6">1.1289</dst>
      <dst id="16">11154.4978</dst>
      <dst id="14">173.5733</dst>
      <dst id="20">271.6978</dst>
      <dst id="11">42.9689</dst>
      <dst id="9">1273.2267</dst>
      <dst id="17">35664.0089</dst>
      <dst id="21">2445.4311</dst>
      <dst id="15">184.2133</dst>
    </src>
    <src id="15">
      <dst id="12">1431.7689</dst>
      <dst id="13">503.0667</dst>
      <dst id="23">1.3689</dst>
      <dst id="18">215.7867</dst>
      <dst id="4">114.2667</dst>
      <dst id="1">398.2756</dst>
      <dst id="5">323.7867</dst>
      <dst id="10">2.3556</dst>
      <dst id="7">135.3067</dst>
      <dst id="2">8.8000</dst>
      <dst id="16">461.4667</dst>
      <dst id="11">17.0489</dst>
      <dst id="9">294.1244</dst>
      <dst id="17">353.6356</dst>
      <dst id="21">10.4889</dst>
    </src>
  </IntraTM>
</TrafficMatrixFile>
