<?xml version="1.0" encoding="UTF-8" standalone="yes"?>
<TrafficMatrixFile xmlns:xsi="http://www.w3.org/2001/XMLSchema-instance" xsi:noNamespaceSchemaLocation="http://totem.run.montefiore.ulg.ac.be/Schema/TrafficMatrix-v1_2.xsd">
  <info>
    <title>Intradomain traffic matrix generated by geant-TM-all.pl</title>
    <date>2005-02-06T23:15:00</date>
    <duration>900</duration>
    <author>Steve Uhlig</author>
    <units>
        <unit type="bandwidth" value="kbps"/>
    </units>
  </info>
  <IntraTM ASID="20965">
    <src id="12">
      <dst id="12">323170.8356</dst>
      <dst id="13">35080.1422</dst>
      <dst id="19">10013.3956</dst>
      <dst id="23">102.8889</dst>
      <dst id="8">2060.8089</dst>
      <dst id="18">82418.9422</dst>
      <dst id="4">101749.9289</dst>
      <dst id="1">18551.8578</dst>
      <dst id="5">3669.9022</dst>
      <dst id="3">631.5733</dst>
      <dst id="10">7336.7289</dst>
      <dst id="22">25639.3422</dst>
      <dst id="7">13461.1111</dst>
      <dst id="2">74107.8311</dst>
      <dst id="6">16.8089</dst>
      <dst id="16">13691.6356</dst>
      <dst id="14">571.3067</dst>
      <dst id="20">21974.2044</dst>
      <dst id="11">197.1378</dst>
      <dst id="9">18537.5200</dst>
      <dst id="17">143162.9333</dst>
      <dst id="21">50954.5333</dst>
      <dst id="15">6746.0978</dst>
    </src>
    <src id="13">
      <dst id="12">60268.8533</dst>
      <dst id="19">21639.1644</dst>
      <dst id="23">2608.4711</dst>
      <dst id="8">17195.4844</dst>
      <dst id="18">4863.9200</dst>
      <dst id="1">14974.3111</dst>
      <dst id="5">17510.0178</dst>
      <dst id="3">4288.4089</dst>
      <dst id="22">25398.9422</dst>
      <dst id="7">42136.7911</dst>
      <dst id="2">89851.7689</dst>
      <dst id="6">2141.8400</dst>
      <dst id="16">9198.9422</dst>
      <dst id="14">2631.6800</dst>
      <dst id="20">20318.6222</dst>
      <dst id="11">927.7867</dst>
      <dst id="9">24286.7911</dst>
      <dst id="17">154377.8222</dst>
      <dst id="21">11904.3200</dst>
      <dst id="15">3435.6267</dst>
    </src>
    <src id="19">
      <dst id="12">15909.1378</dst>
      <dst id="13">12523.2089</dst>
      <dst id="23">237.0489</dst>
      <dst id="8">5.5822</dst>
      <dst id="18">12.4089</dst>
      <dst id="4">15608.1867</dst>
      <dst id="1">1798.6222</dst>
      <dst id="5">194.0444</dst>
      <dst id="3">152.5511</dst>
      <dst id="10">105.2711</dst>
      <dst id="22">241.3511</dst>
      <dst id="7">6921.6089</dst>
      <dst id="2">5131.5822</dst>
      <dst id="6">453.9200</dst>
      <dst id="16">16480.4978</dst>
      <dst id="14">3.0578</dst>
      <dst id="20">6012.7289</dst>
      <dst id="11">223.2089</dst>
      <dst id="9">3661.6178</dst>
      <dst id="17">67355.2000</dst>
      <dst id="21">5204.5067</dst>
      <dst id="15">3.2356</dst>
    </src>
    <src id="23">
      <dst id="12">1125.3689</dst>
      <dst id="13">219.8222</dst>
      <dst id="19">219.4756</dst>
      <dst id="8">859.0578</dst>
      <dst id="18">4568.4711</dst>
      <dst id="4">3880.9422</dst>
      <dst id="1">107.9644</dst>
      <dst id="5">24.7911</dst>
      <dst id="10">1857.4756</dst>
      <dst id="22">133.5289</dst>
      <dst id="7">939.6800</dst>
      <dst id="2">611.4400</dst>
      <dst id="6">0.4711</dst>
      <dst id="16">119.2000</dst>
      <dst id="14">0.3556</dst>
      <dst id="20">13.9467</dst>
      <dst id="9">55.9289</dst>
      <dst id="17">9818.5067</dst>
      <dst id="21">525.4578</dst>
      <dst id="15">161.1378</dst>
    </src>
    <src id="8">
      <dst id="12">58850.6311</dst>
      <dst id="13">1980.6756</dst>
      <dst id="19">29.2000</dst>
      <dst id="23">39.3867</dst>
      <dst id="18">579.6800</dst>
      <dst id="4">4014.3200</dst>
      <dst id="1">11402.6133</dst>
      <dst id="5">8886.9067</dst>
      <dst id="3">69.1911</dst>
      <dst id="10">94.4267</dst>
      <dst id="22">1375.3244</dst>
      <dst id="7">326.6311</dst>
      <dst id="2">217.9378</dst>
      <dst id="6">0.9244</dst>
      <dst id="16">898.9067</dst>
      <dst id="14">2.5333</dst>
      <dst id="20">659.9467</dst>
      <dst id="11">27.7333</dst>
      <dst id="9">223773.0133</dst>
      <dst id="17">375247.3778</dst>
      <dst id="21">250.5156</dst>
      <dst id="15">391.3778</dst>
    </src>
    <src id="18">
      <dst id="12">186847.2978</dst>
      <dst id="13">1273.6000</dst>
      <dst id="19">190.0267</dst>
      <dst id="23">60.3022</dst>
      <dst id="8">134.3289</dst>
      <dst id="4">813.7067</dst>
      <dst id="1">737.0222</dst>
      <dst id="5">547.3511</dst>
      <dst id="3">1152.7022</dst>
      <dst id="10">165.5289</dst>
      <dst id="22">144.7822</dst>
      <dst id="7">187.0133</dst>
      <dst id="2">53653.5289</dst>
      <dst id="6">0.3556</dst>
      <dst id="16">80.0533</dst>
      <dst id="14">0.4267</dst>
      <dst id="20">438.3289</dst>
      <dst id="9">97.3244</dst>
      <dst id="17">15208.4800</dst>
      <dst id="21">1968.7644</dst>
      <dst id="15">2.9422</dst>
    </src>
    <src id="4">
      <dst id="12">15877.1378</dst>
      <dst id="19">4783.8044</dst>
      <dst id="23">429.3422</dst>
      <dst id="8">1603.3333</dst>
      <dst id="18">2648.5778</dst>
      <dst id="4">842.1956</dst>
      <dst id="1">301411.7156</dst>
      <dst id="5">1182.7022</dst>
      <dst id="3">1338.8978</dst>
      <dst id="22">4991.5467</dst>
      <dst id="7">70400.5511</dst>
      <dst id="2">55709.7867</dst>
      <dst id="6">184.9422</dst>
      <dst id="16">1781.4756</dst>
      <dst id="14">1257.1733</dst>
      <dst id="20">1366.1867</dst>
      <dst id="11">956.8444</dst>
      <dst id="9">8264.5956</dst>
      <dst id="17">34911.4489</dst>
      <dst id="21">8566.0000</dst>
      <dst id="15">500.7556</dst>
    </src>
    <src id="1">
      <dst id="12">26358.1244</dst>
      <dst id="13">13779.6800</dst>
      <dst id="19">9297.8933</dst>
      <dst id="23">89.2800</dst>
      <dst id="8">37.9200</dst>
      <dst id="18">13278.7644</dst>
      <dst id="4">6085.5200</dst>
      <dst id="1">57510.4356</dst>
      <dst id="5">818.8267</dst>
      <dst id="3">7406.7644</dst>
      <dst id="10">5845.5644</dst>
      <dst id="22">1175.6444</dst>
      <dst id="7">120297.6267</dst>
      <dst id="2">19594.1156</dst>
      <dst id="6">32.8178</dst>
      <dst id="16">25381.5733</dst>
      <dst id="14">92.9244</dst>
      <dst id="20">983.7333</dst>
      <dst id="11">4706.4267</dst>
      <dst id="9">1199.7511</dst>
      <dst id="17">26130.7556</dst>
      <dst id="21">11737.2622</dst>
      <dst id="15">221.8578</dst>
    </src>
    <src id="5">
      <dst id="12">47448.3378</dst>
      <dst id="13">3164.0089</dst>
      <dst id="19">6933.3333</dst>
      <dst id="23">1.2800</dst>
      <dst id="8">5176.3733</dst>
      <dst id="18">116.4000</dst>
      <dst id="4">5585.3689</dst>
      <dst id="1">5385.6889</dst>
      <dst id="3">256.1778</dst>
      <dst id="10">279.5200</dst>
      <dst id="22">11248.0622</dst>
      <dst id="7">461.0222</dst>
      <dst id="2">4444.9244</dst>
      <dst id="6">0.7111</dst>
      <dst id="16">1068.4533</dst>
      <dst id="14">1.2978</dst>
      <dst id="20">1890.9956</dst>
      <dst id="11">18.4356</dst>
      <dst id="9">69866.8000</dst>
      <dst id="17">401851.0400</dst>
      <dst id="21">312.1333</dst>
      <dst id="15">1904.7644</dst>
    </src>
    <src id="3">
      <dst id="12">8519.6000</dst>
      <dst id="13">3773.0133</dst>
      <dst id="19">2393.2356</dst>
      <dst id="23">459.3156</dst>
      <dst id="8">1750.8178</dst>
      <dst id="18">161.7600</dst>
      <dst id="4">40026.0622</dst>
      <dst id="1">8894.2222</dst>
      <dst id="5">2012.3822</dst>
      <dst id="3">154.9600</dst>
      <dst id="10">585.5111</dst>
      <dst id="22">2594.1156</dst>
      <dst id="7">4168.6044</dst>
      <dst id="2">14029.7600</dst>
      <dst id="6">111.0667</dst>
      <dst id="16">2607.2356</dst>
      <dst id="14">135.8311</dst>
      <dst id="20">293.5644</dst>
      <dst id="11">357.2178</dst>
      <dst id="9">1318.1333</dst>
      <dst id="17">53323.4667</dst>
      <dst id="21">2568.2844</dst>
      <dst id="15">1221.3511</dst>
    </src>
    <src id="10">
      <dst id="12">345101.8756</dst>
      <dst id="19">4027.7244</dst>
      <dst id="23">1065.2444</dst>
      <dst id="8">206224.4356</dst>
      <dst id="18">1595.6444</dst>
      <dst id="1">3191.2089</dst>
      <dst id="5">296653.4044</dst>
      <dst id="3">22824.1156</dst>
      <dst id="22">4164.9600</dst>
      <dst id="7">28687.6800</dst>
      <dst id="2">33656.0178</dst>
      <dst id="6">30312.3644</dst>
      <dst id="16">2805.8400</dst>
      <dst id="14">41786.6578</dst>
      <dst id="20">3639.6533</dst>
      <dst id="11">35239.2800</dst>
      <dst id="9">402745.4222</dst>
      <dst id="17">78304.1778</dst>
      <dst id="21">16866.9511</dst>
      <dst id="15">812.8533</dst>
    </src>
    <src id="22">
      <dst id="12">15006.8178</dst>
      <dst id="13">7010.6578</dst>
      <dst id="19">1780.3111</dst>
      <dst id="23">2474.2756</dst>
      <dst id="8">839.0311</dst>
      <dst id="18">368.6311</dst>
      <dst id="4">16005.7689</dst>
      <dst id="1">368.1422</dst>
      <dst id="5">3117.2800</dst>
      <dst id="3">11.5467</dst>
      <dst id="10">2621.3867</dst>
      <dst id="7">2958.0444</dst>
      <dst id="2">3048.5600</dst>
      <dst id="6">340.8089</dst>
      <dst id="14">88.0889</dst>
      <dst id="11">157.5200</dst>
      <dst id="9">9374.9333</dst>
      <dst id="17">16323.7422</dst>
      <dst id="21">1284.9600</dst>
    </src>
    <src id="7">
      <dst id="12">8173.5200</dst>
      <dst id="13">935.2800</dst>
      <dst id="19">2420.4800</dst>
      <dst id="23">554.6489</dst>
      <dst id="8">656.6578</dst>
      <dst id="18">736.6578</dst>
      <dst id="4">65293.5200</dst>
      <dst id="1">11123.6000</dst>
      <dst id="5">2076.4622</dst>
      <dst id="3">2808.8000</dst>
      <dst id="10">1823.4222</dst>
      <dst id="22">5625.0667</dst>
      <dst id="7">691.5378</dst>
      <dst id="2">17396.2044</dst>
      <dst id="6">2727.7600</dst>
      <dst id="16">1903.8756</dst>
      <dst id="14">874.8000</dst>
      <dst id="20">2791.4578</dst>
      <dst id="11">301.2889</dst>
      <dst id="9">1140.7733</dst>
      <dst id="17">30331.3867</dst>
      <dst id="21">6226.0978</dst>
      <dst id="15">979.1378</dst>
    </src>
    <src id="2">
      <dst id="12">129917.5289</dst>
      <dst id="13">36833.2267</dst>
      <dst id="19">14500.0711</dst>
      <dst id="23">3.5378</dst>
      <dst id="8">738.8889</dst>
      <dst id="18">65306.8178</dst>
      <dst id="4">69473.3067</dst>
      <dst id="1">19801.5467</dst>
      <dst id="5">1281.6800</dst>
      <dst id="3">379.4489</dst>
      <dst id="10">2943.6178</dst>
      <dst id="22">4952.7733</dst>
      <dst id="7">19688.6756</dst>
      <dst id="2">1887.2533</dst>
      <dst id="6">23379.5733</dst>
      <dst id="16">1637.3600</dst>
      <dst id="14">166.2222</dst>
      <dst id="20">524.9689</dst>
      <dst id="11">4447.3778</dst>
      <dst id="9">2526.3733</dst>
      <dst id="17">31460.4444</dst>
      <dst id="21">8061.7422</dst>
      <dst id="15">805.2444</dst>
    </src>
    <src id="6">
      <dst id="12">4104.9422</dst>
      <dst id="13">130.1867</dst>
      <dst id="19">54.2044</dst>
      <dst id="23">23.2089</dst>
      <dst id="18">63.5289</dst>
      <dst id="4">175.5644</dst>
      <dst id="1">324.9689</dst>
      <dst id="5">136.1156</dst>
      <dst id="3">11.4667</dst>
      <dst id="10">2.7022</dst>
      <dst id="22">50.6489</dst>
      <dst id="7">397.0756</dst>
      <dst id="2">7737.0933</dst>
      <dst id="16">43.8400</dst>
      <dst id="14">1.3067</dst>
      <dst id="11">34.4000</dst>
      <dst id="9">53.3867</dst>
      <dst id="17">23586.5956</dst>
      <dst id="21">112.6311</dst>
    </src>
    <src id="16">
      <dst id="12">3565.6800</dst>
      <dst id="13">1556.0800</dst>
      <dst id="19">4071.1644</dst>
      <dst id="23">9.2267</dst>
      <dst id="8">11324.8622</dst>
      <dst id="18">43.7956</dst>
      <dst id="4">3457.9289</dst>
      <dst id="1">24249.5556</dst>
      <dst id="5">7419.4044</dst>
      <dst id="3">79.1556</dst>
      <dst id="10">341.2533</dst>
      <dst id="7">1436.3200</dst>
      <dst id="2">1887.0578</dst>
      <dst id="6">89.0756</dst>
      <dst id="16">27.8933</dst>
      <dst id="14">11.5378</dst>
      <dst id="11">14.1422</dst>
      <dst id="9">10587.2356</dst>
      <dst id="17">6806.9689</dst>
      <dst id="21">671.8222</dst>
    </src>
    <src id="14">
      <dst id="12">5081.2622</dst>
      <dst id="13">472.1778</dst>
      <dst id="19">66.0711</dst>
      <dst id="23">0.3556</dst>
      <dst id="8">63.5378</dst>
      <dst id="4">1593.2889</dst>
      <dst id="1">1539.7778</dst>
      <dst id="5">14.0000</dst>
      <dst id="3">270.9689</dst>
      <dst id="10">71.8667</dst>
      <dst id="22">20.4089</dst>
      <dst id="7">111.1111</dst>
      <dst id="2">5252.0622</dst>
      <dst id="16">104.0356</dst>
      <dst id="20">1.2800</dst>
      <dst id="11">0.4622</dst>
      <dst id="9">125.9911</dst>
      <dst id="17">41868.0800</dst>
      <dst id="21">268.0089</dst>
    </src>
    <src id="20">
      <dst id="12">12507.3244</dst>
      <dst id="13">2104.7022</dst>
      <dst id="19">311.4133</dst>
      <dst id="23">28.6933</dst>
      <dst id="8">384.4622</dst>
      <dst id="18">738.1600</dst>
      <dst id="4">5075.1200</dst>
      <dst id="1">10751.2533</dst>
      <dst id="5">1949.2622</dst>
      <dst id="3">360.7111</dst>
      <dst id="10">570.5956</dst>
      <dst id="7">5668.3467</dst>
      <dst id="2">8604.6311</dst>
      <dst id="14">3.8222</dst>
      <dst id="11">47.5822</dst>
      <dst id="9">21051.1822</dst>
      <dst id="17">21519.2267</dst>
      <dst id="21">14692.5156</dst>
    </src>
    <src id="11">
      <dst id="12">85304.4000</dst>
      <dst id="13">5528.3556</dst>
      <dst id="19">1365.9111</dst>
      <dst id="23">106.8178</dst>
      <dst id="8">1190.2844</dst>
      <dst id="18">347.4311</dst>
      <dst id="4">6036.4089</dst>
      <dst id="1">2319.4133</dst>
      <dst id="5">2042.3733</dst>
      <dst id="3">192.9600</dst>
      <dst id="10">777.3778</dst>
      <dst id="22">2879.6356</dst>
      <dst id="7">580.9778</dst>
      <dst id="2">130264.1067</dst>
      <dst id="6">9.0222</dst>
      <dst id="16">2275.1200</dst>
      <dst id="14">287.4311</dst>
      <dst id="20">1133.3689</dst>
      <dst id="11">3985.9733</dst>
      <dst id="9">2472.5956</dst>
      <dst id="17">792541.7422</dst>
      <dst id="21">1062.2222</dst>
      <dst id="15">973.2444</dst>
    </src>
    <src id="9">
      <dst id="12">91837.9022</dst>
      <dst id="13">8678.7200</dst>
      <dst id="19">366.3467</dst>
      <dst id="23">5.2267</dst>
      <dst id="8">199212.9422</dst>
      <dst id="18">71.7600</dst>
      <dst id="4">10853.3600</dst>
      <dst id="1">12726.6933</dst>
      <dst id="5">962.3644</dst>
      <dst id="3">2.7378</dst>
      <dst id="10">2651.1733</dst>
      <dst id="22">31636.3289</dst>
      <dst id="7">4777.8578</dst>
      <dst id="2">3976.8000</dst>
      <dst id="6">1.0667</dst>
      <dst id="16">1711.8311</dst>
      <dst id="14">108.6311</dst>
      <dst id="20">8238.5333</dst>
      <dst id="11">71.8222</dst>
      <dst id="9">578120.8533</dst>
      <dst id="17">488604.2578</dst>
      <dst id="21">1328.6400</dst>
      <dst id="15">5519.2800</dst>
    </src>
    <src id="17">
      <dst id="12">259396.8444</dst>
      <dst id="13">9159.1556</dst>
      <dst id="19">2690.6044</dst>
      <dst id="23">248.7911</dst>
      <dst id="8">960.9956</dst>
      <dst id="18">714.9244</dst>
      <dst id="4">46083.9200</dst>
      <dst id="1">10819.7244</dst>
      <dst id="5">252256.5600</dst>
      <dst id="3">7730.1333</dst>
      <dst id="10">5126.0800</dst>
      <dst id="22">13198.4178</dst>
      <dst id="7">27103.6711</dst>
      <dst id="2">16019.3956</dst>
      <dst id="6">708.3200</dst>
      <dst id="16">19569.5733</dst>
      <dst id="14">33024.0089</dst>
      <dst id="20">7741.8578</dst>
      <dst id="11">38463.0044</dst>
      <dst id="9">4827.3067</dst>
      <dst id="17">59581.4933</dst>
      <dst id="21">21185.6622</dst>
      <dst id="15">843.1200</dst>
    </src>
    <src id="21">
      <dst id="12">18404.5244</dst>
      <dst id="13">927.6267</dst>
      <dst id="19">450.8000</dst>
      <dst id="23">90.7733</dst>
      <dst id="8">281.9200</dst>
      <dst id="18">4208.2489</dst>
      <dst id="4">9886.0356</dst>
      <dst id="1">3241.9111</dst>
      <dst id="5">829.3067</dst>
      <dst id="3">3830.2489</dst>
      <dst id="10">1146.5867</dst>
      <dst id="22">4589.8044</dst>
      <dst id="7">5904.5067</dst>
      <dst id="2">9272.9600</dst>
      <dst id="6">25.1289</dst>
      <dst id="16">1119.2711</dst>
      <dst id="14">93.0578</dst>
      <dst id="20">853.2622</dst>
      <dst id="11">82.2400</dst>
      <dst id="9">914.7378</dst>
      <dst id="17">27960.4533</dst>
      <dst id="21">3670.3111</dst>
      <dst id="15">43.0489</dst>
    </src>
    <src id="15">
      <dst id="12">1539.7067</dst>
      <dst id="13">1161.4667</dst>
      <dst id="19">17.5200</dst>
      <dst id="23">2.8444</dst>
      <dst id="8">169.9556</dst>
      <dst id="18">108.1867</dst>
      <dst id="4">931.8133</dst>
      <dst id="1">65.8133</dst>
      <dst id="5">4768.0533</dst>
      <dst id="3">28.0711</dst>
      <dst id="10">911.5556</dst>
      <dst id="7">84.0978</dst>
      <dst id="2">109.2356</dst>
      <dst id="11">66.2311</dst>
      <dst id="9">21127.8489</dst>
      <dst id="17">11213.4044</dst>
      <dst id="21">59.1111</dst>
    </src>
  </IntraTM>
</TrafficMatrixFile>
