<?xml version="1.0" encoding="UTF-8" standalone="yes"?>
<TrafficMatrixFile xmlns:xsi="http://www.w3.org/2001/XMLSchema-instance" xsi:noNamespaceSchemaLocation="http://totem.run.montefiore.ulg.ac.be/Schema/TrafficMatrix-v1_2.xsd">
  <info>
    <title>Intradomain traffic matrix generated by geant-TM-all.pl</title>
    <date>2005-04-07T06:15:00</date>
    <duration>900</duration>
    <author>Steve Uhlig</author>
    <units>
        <unit type="bandwidth" value="kbps"/>
    </units>
  </info>
  <IntraTM ASID="20965">
    <src id="12">
      <dst id="12">377399.5822</dst>
      <dst id="13">35584.6667</dst>
      <dst id="19">5868.8089</dst>
      <dst id="23">2785.7244</dst>
      <dst id="8">348.3111</dst>
      <dst id="18">59186.1778</dst>
      <dst id="4">3004.4000</dst>
      <dst id="1">24636.5956</dst>
      <dst id="5">2340.1778</dst>
      <dst id="3">244.7467</dst>
      <dst id="10">4072.7467</dst>
      <dst id="22">13522.8533</dst>
      <dst id="7">270.7200</dst>
      <dst id="2">34798.0889</dst>
      <dst id="16">14018.4978</dst>
      <dst id="14">260.2756</dst>
      <dst id="20">5442.2222</dst>
      <dst id="11">144.0178</dst>
      <dst id="9">4417.1556</dst>
      <dst id="17">67162.0889</dst>
      <dst id="21">1541.1733</dst>
      <dst id="15">1232.9956</dst>
    </src>
    <src id="13">
      <dst id="12">20224.4444</dst>
      <dst id="13">2152.5422</dst>
      <dst id="19">3201.6267</dst>
      <dst id="23">28.0978</dst>
      <dst id="8">173.0756</dst>
      <dst id="18">94.8889</dst>
      <dst id="4">1.6356</dst>
      <dst id="1">454.6933</dst>
      <dst id="5">13485.1111</dst>
      <dst id="3">2.7378</dst>
      <dst id="10">1.2444</dst>
      <dst id="22">3875.6622</dst>
      <dst id="7">1842.0622</dst>
      <dst id="2">10271.9733</dst>
      <dst id="6">0.5333</dst>
      <dst id="16">11576.3556</dst>
      <dst id="14">56.3733</dst>
      <dst id="20">13718.6489</dst>
      <dst id="11">65.1467</dst>
      <dst id="9">1667.9733</dst>
      <dst id="17">26968.8978</dst>
      <dst id="21">1975.0044</dst>
      <dst id="15">283.5111</dst>
    </src>
    <src id="19">
      <dst id="12">60543.5556</dst>
      <dst id="13">4198.8711</dst>
      <dst id="23">7.3956</dst>
      <dst id="8">28.8000</dst>
      <dst id="4">259.4667</dst>
      <dst id="1">274.4533</dst>
      <dst id="5">135.7333</dst>
      <dst id="3">1.5911</dst>
      <dst id="10">337.0133</dst>
      <dst id="22">1.4578</dst>
      <dst id="7">877.2089</dst>
      <dst id="2">502.5244</dst>
      <dst id="16">417.2089</dst>
      <dst id="14">4.1956</dst>
      <dst id="20">13.3333</dst>
      <dst id="11">1.4933</dst>
      <dst id="9">1184.7467</dst>
      <dst id="17">4706.5867</dst>
      <dst id="21">273.3511</dst>
      <dst id="15">2.1067</dst>
    </src>
    <src id="23">
      <dst id="12">8191.8933</dst>
      <dst id="13">781.3333</dst>
      <dst id="19">224.3378</dst>
      <dst id="18">1.0844</dst>
      <dst id="4">99.1467</dst>
      <dst id="1">148.8444</dst>
      <dst id="10">190.1689</dst>
      <dst id="22">256.1067</dst>
      <dst id="7">26.6489</dst>
      <dst id="2">1187.6889</dst>
      <dst id="16">8.4444</dst>
      <dst id="14">12.6222</dst>
      <dst id="20">1.5822</dst>
      <dst id="11">59.6356</dst>
      <dst id="9">2.8267</dst>
      <dst id="17">373.9556</dst>
      <dst id="21">972.1422</dst>
    </src>
    <src id="8">
      <dst id="12">8586.1511</dst>
      <dst id="13">138.6044</dst>
      <dst id="19">59.6889</dst>
      <dst id="4">48.2933</dst>
      <dst id="1">877.0844</dst>
      <dst id="5">183.5733</dst>
      <dst id="3">1106.8889</dst>
      <dst id="10">21.2267</dst>
      <dst id="22">10.8889</dst>
      <dst id="2">23.6978</dst>
      <dst id="16">247532.9244</dst>
      <dst id="14">12.6222</dst>
      <dst id="11">38.0444</dst>
      <dst id="9">78370.9956</dst>
      <dst id="17">18057.9289</dst>
      <dst id="21">0.7556</dst>
      <dst id="15">104.9244</dst>
    </src>
    <src id="18">
      <dst id="12">157610.7911</dst>
      <dst id="13">188.0622</dst>
      <dst id="19">9.0311</dst>
      <dst id="23">1.9556</dst>
      <dst id="8">0.9956</dst>
      <dst id="4">200.1689</dst>
      <dst id="1">1228.8356</dst>
      <dst id="5">493.6089</dst>
      <dst id="3">2420.3644</dst>
      <dst id="10">135.0400</dst>
      <dst id="22">242.1422</dst>
      <dst id="7">17.0756</dst>
      <dst id="2">11047.4133</dst>
      <dst id="16">502.1422</dst>
      <dst id="20">2317.2356</dst>
      <dst id="11">4.4089</dst>
      <dst id="9">187.9911</dst>
      <dst id="17">5133.4133</dst>
      <dst id="21">777.1822</dst>
      <dst id="15">0.9422</dst>
    </src>
    <src id="4">
      <dst id="12">58574.0978</dst>
      <dst id="13">12.7378</dst>
      <dst id="19">33813.7333</dst>
      <dst id="23">767.5467</dst>
      <dst id="8">3293.3600</dst>
      <dst id="18">11981.6444</dst>
      <dst id="4">9461.6889</dst>
      <dst id="1">105851.1289</dst>
      <dst id="5">8282.5689</dst>
      <dst id="3">24.0800</dst>
      <dst id="22">7393.8400</dst>
      <dst id="7">102.2844</dst>
      <dst id="2">221524.9689</dst>
      <dst id="16">201649.7778</dst>
      <dst id="14">8745.3956</dst>
      <dst id="11">409.3689</dst>
      <dst id="9">38330.8000</dst>
      <dst id="17">139146.2756</dst>
      <dst id="21">5900.6489</dst>
      <dst id="15">2493.3956</dst>
    </src>
    <src id="1">
      <dst id="12">462908.8889</dst>
      <dst id="13">4262.0267</dst>
      <dst id="19">252.4089</dst>
      <dst id="23">95.7333</dst>
      <dst id="8">135.6533</dst>
      <dst id="18">17950.4622</dst>
      <dst id="4">561.2889</dst>
      <dst id="1">30802.1156</dst>
      <dst id="5">814.6756</dst>
      <dst id="3">159.7244</dst>
      <dst id="10">825.8400</dst>
      <dst id="22">110.4444</dst>
      <dst id="7">369.0756</dst>
      <dst id="2">3114.8089</dst>
      <dst id="16">350339.4756</dst>
      <dst id="14">117.1556</dst>
      <dst id="20">181.9733</dst>
      <dst id="11">45.6622</dst>
      <dst id="9">1858.9156</dst>
      <dst id="17">70726.3289</dst>
      <dst id="21">7132.0889</dst>
      <dst id="15">112.4889</dst>
    </src>
    <src id="5">
      <dst id="12">28391.0311</dst>
      <dst id="13">1815.3422</dst>
      <dst id="19">182.9689</dst>
      <dst id="8">392.8089</dst>
      <dst id="18">166.4622</dst>
      <dst id="4">287.2356</dst>
      <dst id="1">4086.4000</dst>
      <dst id="3">440.5689</dst>
      <dst id="10">1165.7778</dst>
      <dst id="22">1094.1511</dst>
      <dst id="2">209.4756</dst>
      <dst id="16">311375.8133</dst>
      <dst id="14">0.3556</dst>
      <dst id="11">6.7200</dst>
      <dst id="9">58333.6889</dst>
      <dst id="17">61531.3956</dst>
      <dst id="21">156.9067</dst>
      <dst id="15">86.4267</dst>
    </src>
    <src id="3">
      <dst id="12">1772.2222</dst>
      <dst id="13">21140.7111</dst>
      <dst id="19">2758.6400</dst>
      <dst id="23">10.3289</dst>
      <dst id="8">35.8222</dst>
      <dst id="18">352.8533</dst>
      <dst id="4">623.0400</dst>
      <dst id="1">30153.3156</dst>
      <dst id="5">362.5778</dst>
      <dst id="3">151.7333</dst>
      <dst id="10">416.0000</dst>
      <dst id="22">342.6311</dst>
      <dst id="7">275.1911</dst>
      <dst id="2">4440.2844</dst>
      <dst id="16">10978.2844</dst>
      <dst id="14">299.4311</dst>
      <dst id="20">95.1556</dst>
      <dst id="11">479.6356</dst>
      <dst id="9">348.5956</dst>
      <dst id="17">33181.5022</dst>
      <dst id="21">1435.6889</dst>
      <dst id="15">4.9244</dst>
    </src>
    <src id="10">
      <dst id="12">10176.4444</dst>
      <dst id="13">5.4933</dst>
      <dst id="19">664.5600</dst>
      <dst id="23">5329.6533</dst>
      <dst id="8">187.8489</dst>
      <dst id="18">4874.4089</dst>
      <dst id="1">449.7778</dst>
      <dst id="5">6484.9422</dst>
      <dst id="3">33.1378</dst>
      <dst id="22">94.1600</dst>
      <dst id="7">3.6267</dst>
      <dst id="2">18786.9422</dst>
      <dst id="16">18910.4356</dst>
      <dst id="14">1047.6800</dst>
      <dst id="20">3644.8978</dst>
      <dst id="11">22.3022</dst>
      <dst id="9">4474.4089</dst>
      <dst id="17">22954.3556</dst>
      <dst id="21">3992.3556</dst>
      <dst id="15">297.6178</dst>
    </src>
    <src id="22">
      <dst id="12">10678.5689</dst>
      <dst id="13">3739.0667</dst>
      <dst id="19">17.7067</dst>
      <dst id="23">9.6000</dst>
      <dst id="8">2085.5644</dst>
      <dst id="18">299.6800</dst>
      <dst id="4">3528.9956</dst>
      <dst id="1">305.0222</dst>
      <dst id="5">1596.4800</dst>
      <dst id="3">5.3156</dst>
      <dst id="10">514.7378</dst>
      <dst id="7">52.1333</dst>
      <dst id="2">986.1333</dst>
      <dst id="16">119.0044</dst>
      <dst id="14">31.3600</dst>
      <dst id="11">614.9333</dst>
      <dst id="9">941.4222</dst>
      <dst id="17">6647.3422</dst>
      <dst id="21">1178.0000</dst>
    </src>
    <src id="7">
      <dst id="12">15173.7067</dst>
      <dst id="13">19032.6578</dst>
      <dst id="19">213.5467</dst>
      <dst id="23">4.0000</dst>
      <dst id="8">14.6133</dst>
      <dst id="18">226.5956</dst>
      <dst id="4">2608.9867</dst>
      <dst id="1">8996.9956</dst>
      <dst id="5">160.8800</dst>
      <dst id="3">55.5733</dst>
      <dst id="10">698.0089</dst>
      <dst id="22">475.8044</dst>
      <dst id="2">795.9644</dst>
      <dst id="16">114.0978</dst>
      <dst id="14">64.1778</dst>
      <dst id="20">134.0711</dst>
      <dst id="11">885.7333</dst>
      <dst id="9">213.4933</dst>
      <dst id="17">3845.9111</dst>
      <dst id="21">2858.4978</dst>
      <dst id="15">4.5689</dst>
    </src>
    <src id="2">
      <dst id="12">105868.9511</dst>
      <dst id="13">69788.5067</dst>
      <dst id="19">2325.6711</dst>
      <dst id="23">0.9244</dst>
      <dst id="8">60.2489</dst>
      <dst id="18">24650.6044</dst>
      <dst id="4">5682.8178</dst>
      <dst id="1">29623.3600</dst>
      <dst id="5">129.2267</dst>
      <dst id="3">19.5911</dst>
      <dst id="10">3670.0711</dst>
      <dst id="22">487.4044</dst>
      <dst id="7">3937.6000</dst>
      <dst id="2">3034.1422</dst>
      <dst id="16">2582.0800</dst>
      <dst id="14">142.3378</dst>
      <dst id="20">190.7556</dst>
      <dst id="11">1133.2711</dst>
      <dst id="9">5034.8978</dst>
      <dst id="17">23491.8222</dst>
      <dst id="21">1490.5422</dst>
      <dst id="15">164.1244</dst>
    </src>
    <src id="6">
      <dst id="12">340.2222</dst>
      <dst id="13">16.1244</dst>
      <dst id="19">5.3689</dst>
      <dst id="4">27.6889</dst>
      <dst id="1">246.8800</dst>
      <dst id="5">0.4267</dst>
      <dst id="3">1.2089</dst>
      <dst id="10">0.3556</dst>
      <dst id="22">14.6222</dst>
      <dst id="2">1759.4667</dst>
      <dst id="16">42.0800</dst>
      <dst id="20">2.5511</dst>
      <dst id="9">40.0178</dst>
      <dst id="17">20611.8133</dst>
      <dst id="15">0.3378</dst>
    </src>
    <src id="16">
      <dst id="12">105231.1378</dst>
      <dst id="13">1070.5333</dst>
      <dst id="19">3018.6311</dst>
      <dst id="23">37.8667</dst>
      <dst id="8">100626.9156</dst>
      <dst id="18">9.2622</dst>
      <dst id="4">325.9911</dst>
      <dst id="1">13022.5244</dst>
      <dst id="5">275475.3511</dst>
      <dst id="3">2022.2044</dst>
      <dst id="10">683.1378</dst>
      <dst id="2">757.0756</dst>
      <dst id="16">24445.4400</dst>
      <dst id="14">45176.7556</dst>
      <dst id="11">16310.9778</dst>
      <dst id="9">216303.5733</dst>
      <dst id="17">3101.5733</dst>
      <dst id="21">170.1333</dst>
    </src>
    <src id="14">
      <dst id="12">1211.2356</dst>
      <dst id="13">836.8978</dst>
      <dst id="19">34.1156</dst>
      <dst id="23">0.5244</dst>
      <dst id="8">1.1289</dst>
      <dst id="18">0.4622</dst>
      <dst id="4">377.5911</dst>
      <dst id="1">911.3244</dst>
      <dst id="5">0.4089</dst>
      <dst id="3">1080.7822</dst>
      <dst id="10">408.0000</dst>
      <dst id="22">0.3556</dst>
      <dst id="7">4.1156</dst>
      <dst id="2">1347.5467</dst>
      <dst id="16">4050.7022</dst>
      <dst id="20">12.2222</dst>
      <dst id="11">27.1378</dst>
      <dst id="9">59.0667</dst>
      <dst id="17">31916.1067</dst>
      <dst id="21">110.9600</dst>
    </src>
    <src id="20">
      <dst id="12">5484.5244</dst>
      <dst id="13">2081.4489</dst>
      <dst id="19">0.9333</dst>
      <dst id="8">287.1911</dst>
      <dst id="18">178.4000</dst>
      <dst id="4">235.7689</dst>
      <dst id="1">75.7778</dst>
      <dst id="5">3957.3511</dst>
      <dst id="10">1240.4800</dst>
      <dst id="7">20.4444</dst>
      <dst id="2">1654.5867</dst>
      <dst id="16">9339.2356</dst>
      <dst id="14">8.0356</dst>
      <dst id="20">45.2178</dst>
      <dst id="11">0.7644</dst>
      <dst id="9">512.0711</dst>
      <dst id="17">4810.6222</dst>
      <dst id="21">335.8756</dst>
    </src>
    <src id="11">
      <dst id="12">26670.9067</dst>
      <dst id="13">3750.6044</dst>
      <dst id="19">259.5378</dst>
      <dst id="23">332.7022</dst>
      <dst id="8">116.7022</dst>
      <dst id="18">268.5600</dst>
      <dst id="4">700.0533</dst>
      <dst id="1">4323.2800</dst>
      <dst id="5">1580.6222</dst>
      <dst id="3">687.5022</dst>
      <dst id="10">826.9244</dst>
      <dst id="22">328.8711</dst>
      <dst id="7">1.3244</dst>
      <dst id="2">54356.0978</dst>
      <dst id="16">13076.0533</dst>
      <dst id="14">107.2000</dst>
      <dst id="20">98.0533</dst>
      <dst id="11">2006.2844</dst>
      <dst id="9">4144.5511</dst>
      <dst id="17">621142.0711</dst>
      <dst id="21">1125.8844</dst>
      <dst id="15">141.8844</dst>
    </src>
    <src id="9">
      <dst id="12">34021.9022</dst>
      <dst id="13">2666.7111</dst>
      <dst id="19">64.8267</dst>
      <dst id="8">59613.1200</dst>
      <dst id="18">79.9644</dst>
      <dst id="4">1027.8578</dst>
      <dst id="1">10835.1733</dst>
      <dst id="5">1167.9911</dst>
      <dst id="3">806.7822</dst>
      <dst id="10">269.3778</dst>
      <dst id="22">51.2889</dst>
      <dst id="2">1113.9378</dst>
      <dst id="16">538950.2578</dst>
      <dst id="14">0.8178</dst>
      <dst id="11">7.0756</dst>
      <dst id="9">287068.5778</dst>
      <dst id="17">47510.9511</dst>
      <dst id="21">195.7067</dst>
      <dst id="15">1154.9600</dst>
    </src>
    <src id="17">
      <dst id="12">73982.4622</dst>
      <dst id="13">16686.1689</dst>
      <dst id="19">981.6000</dst>
      <dst id="23">96.7911</dst>
      <dst id="8">153.9022</dst>
      <dst id="18">212.1689</dst>
      <dst id="4">3174.3467</dst>
      <dst id="1">4785.4578</dst>
      <dst id="5">139061.6622</dst>
      <dst id="3">20364.6222</dst>
      <dst id="10">5832.0178</dst>
      <dst id="22">3413.7156</dst>
      <dst id="7">555.6889</dst>
      <dst id="2">10722.0356</dst>
      <dst id="16">60360.7644</dst>
      <dst id="14">18919.2533</dst>
      <dst id="20">315.2267</dst>
      <dst id="11">9832.1244</dst>
      <dst id="9">4694.8889</dst>
      <dst id="17">18858.3822</dst>
      <dst id="21">1960.5333</dst>
      <dst id="15">378.1867</dst>
    </src>
    <src id="21">
      <dst id="12">2816.5778</dst>
      <dst id="13">4281.5644</dst>
      <dst id="19">536.4356</dst>
      <dst id="23">85.2622</dst>
      <dst id="8">245.0222</dst>
      <dst id="18">541.6000</dst>
      <dst id="4">297.2444</dst>
      <dst id="1">10127.5467</dst>
      <dst id="5">767.3244</dst>
      <dst id="3">5087.7600</dst>
      <dst id="10">300.0622</dst>
      <dst id="22">102.3378</dst>
      <dst id="7">235.8489</dst>
      <dst id="2">3774.0000</dst>
      <dst id="16">9912.9156</dst>
      <dst id="14">110.1067</dst>
      <dst id="20">217.1644</dst>
      <dst id="11">453.5022</dst>
      <dst id="9">2121.1111</dst>
      <dst id="17">20389.5111</dst>
      <dst id="21">2711.8756</dst>
      <dst id="15">116.5600</dst>
    </src>
    <src id="15">
      <dst id="12">529.5378</dst>
      <dst id="13">375.7422</dst>
      <dst id="19">0.4711</dst>
      <dst id="23">1.1378</dst>
      <dst id="8">5.1911</dst>
      <dst id="18">38.9333</dst>
      <dst id="4">23.7956</dst>
      <dst id="1">52.3467</dst>
      <dst id="5">183.6533</dst>
      <dst id="10">286.6756</dst>
      <dst id="2">52.3911</dst>
      <dst id="16">520.3111</dst>
      <dst id="14">1.1200</dst>
      <dst id="11">38.3289</dst>
      <dst id="9">1769.3156</dst>
      <dst id="17">4965.7689</dst>
      <dst id="21">276.1422</dst>
    </src>
  </IntraTM>
</TrafficMatrixFile>
