<?xml version="1.0" encoding="UTF-8" standalone="yes"?>
<TrafficMatrixFile xmlns:xsi="http://www.w3.org/2001/XMLSchema-instance" xsi:noNamespaceSchemaLocation="http://totem.run.montefiore.ulg.ac.be/Schema/TrafficMatrix-v1_2.xsd">
  <info>
    <title>Intradomain traffic matrix generated by geant-TM-all.pl</title>
    <date>2005-04-15T15:15:00</date>
    <duration>900</duration>
    <author>Steve Uhlig</author>
    <units>
        <unit type="bandwidth" value="kbps"/>
    </units>
  </info>
  <IntraTM ASID="20965">
    <src id="12">
      <dst id="12">341499.2000</dst>
      <dst id="13">28662.3289</dst>
      <dst id="19">6176.2311</dst>
      <dst id="23">1942.8800</dst>
      <dst id="8">197.6533</dst>
      <dst id="18">28394.2844</dst>
      <dst id="4">5982.8444</dst>
      <dst id="1">36797.2800</dst>
      <dst id="5">1636.8711</dst>
      <dst id="3">594.9333</dst>
      <dst id="10">2734.7644</dst>
      <dst id="22">683.2889</dst>
      <dst id="7">666.3556</dst>
      <dst id="2">4905.5911</dst>
      <dst id="16">13023.6178</dst>
      <dst id="14">800.9244</dst>
      <dst id="20">545.6889</dst>
      <dst id="11">260.3467</dst>
      <dst id="9">25474.0800</dst>
      <dst id="17">21990.0889</dst>
      <dst id="21">462.6933</dst>
      <dst id="15">394.3911</dst>
    </src>
    <src id="13">
      <dst id="12">6660.0000</dst>
      <dst id="13">208.1511</dst>
      <dst id="19">1816.0622</dst>
      <dst id="23">33.2978</dst>
      <dst id="8">649.7867</dst>
      <dst id="18">1530.0356</dst>
      <dst id="4">3.0578</dst>
      <dst id="1">31799.3689</dst>
      <dst id="5">5663.4489</dst>
      <dst id="3">22.7911</dst>
      <dst id="22">5402.0978</dst>
      <dst id="7">505.9378</dst>
      <dst id="2">1126.3289</dst>
      <dst id="16">175.3867</dst>
      <dst id="14">155.6000</dst>
      <dst id="20">13051.7422</dst>
      <dst id="11">382.1067</dst>
      <dst id="9">551.7956</dst>
      <dst id="17">4861.8578</dst>
      <dst id="21">319.1289</dst>
      <dst id="15">208.4178</dst>
    </src>
    <src id="19">
      <dst id="12">38591.0578</dst>
      <dst id="13">1098.5422</dst>
      <dst id="23">0.9867</dst>
      <dst id="8">0.4978</dst>
      <dst id="18">0.4978</dst>
      <dst id="4">109.2356</dst>
      <dst id="1">19074.6133</dst>
      <dst id="5">10.4889</dst>
      <dst id="3">2.7733</dst>
      <dst id="10">81.3244</dst>
      <dst id="22">2262.4711</dst>
      <dst id="7">287.5911</dst>
      <dst id="2">4272.4978</dst>
      <dst id="16">47.2622</dst>
      <dst id="14">8.6489</dst>
      <dst id="20">6.1956</dst>
      <dst id="11">5.6444</dst>
      <dst id="9">15.6267</dst>
      <dst id="17">1897.2889</dst>
      <dst id="21">166.1067</dst>
      <dst id="15">3.9111</dst>
    </src>
    <src id="23">
      <dst id="12">1673.1289</dst>
      <dst id="13">837.5289</dst>
      <dst id="19">42.9511</dst>
      <dst id="18">1761.7067</dst>
      <dst id="4">77.5467</dst>
      <dst id="1">122.8089</dst>
      <dst id="5">13.3333</dst>
      <dst id="10">31.6622</dst>
      <dst id="22">760.9067</dst>
      <dst id="7">33.1911</dst>
      <dst id="2">312.1600</dst>
      <dst id="14">29.6444</dst>
      <dst id="11">90.2222</dst>
      <dst id="9">15.5911</dst>
      <dst id="17">1729.6711</dst>
      <dst id="21">29.3600</dst>
    </src>
    <src id="8">
      <dst id="12">8305.0844</dst>
      <dst id="13">823.3778</dst>
      <dst id="19">0.4711</dst>
      <dst id="23">0.6933</dst>
      <dst id="18">0.4356</dst>
      <dst id="4">392.0267</dst>
      <dst id="1">1731.5733</dst>
      <dst id="5">318.5511</dst>
      <dst id="3">784.0089</dst>
      <dst id="10">73.8667</dst>
      <dst id="22">0.9156</dst>
      <dst id="2">8.6400</dst>
      <dst id="16">208406.6756</dst>
      <dst id="14">4.0267</dst>
      <dst id="9">47647.3511</dst>
      <dst id="17">18680.6400</dst>
      <dst id="21">0.8178</dst>
      <dst id="15">0.3556</dst>
    </src>
    <src id="18">
      <dst id="12">64988.5600</dst>
      <dst id="13">652.2844</dst>
      <dst id="19">13.3333</dst>
      <dst id="23">31.4844</dst>
      <dst id="8">0.7111</dst>
      <dst id="4">112.1067</dst>
      <dst id="1">8877.6356</dst>
      <dst id="5">25.9644</dst>
      <dst id="3">503.5733</dst>
      <dst id="10">1.2800</dst>
      <dst id="22">77.0578</dst>
      <dst id="7">67.0044</dst>
      <dst id="2">1640.1067</dst>
      <dst id="16">113.1822</dst>
      <dst id="14">1.2800</dst>
      <dst id="20">3192.4711</dst>
      <dst id="11">4.9156</dst>
      <dst id="9">4616.4356</dst>
      <dst id="17">2294.4089</dst>
      <dst id="21">345.9111</dst>
    </src>
    <src id="4">
      <dst id="12">17037.0400</dst>
      <dst id="13">12.9156</dst>
      <dst id="19">4839.5289</dst>
      <dst id="23">145.3333</dst>
      <dst id="8">494.0356</dst>
      <dst id="18">1777.8667</dst>
      <dst id="4">848.0711</dst>
      <dst id="1">104660.1956</dst>
      <dst id="5">4277.6267</dst>
      <dst id="3">30.2489</dst>
      <dst id="22">2513.6533</dst>
      <dst id="2">51206.8267</dst>
      <dst id="16">50883.5289</dst>
      <dst id="14">2171.2089</dst>
      <dst id="11">327.9200</dst>
      <dst id="9">15481.3956</dst>
      <dst id="17">32065.8400</dst>
      <dst id="21">4717.7244</dst>
      <dst id="15">622.0089</dst>
    </src>
    <src id="1">
      <dst id="12">30138.8356</dst>
      <dst id="13">21365.0311</dst>
      <dst id="19">4668.6044</dst>
      <dst id="23">105.7778</dst>
      <dst id="8">44.2311</dst>
      <dst id="18">13316.8533</dst>
      <dst id="4">251.4400</dst>
      <dst id="1">458693.7956</dst>
      <dst id="5">307.3333</dst>
      <dst id="3">10.9867</dst>
      <dst id="10">1176.5867</dst>
      <dst id="22">170.6489</dst>
      <dst id="7">1467.9644</dst>
      <dst id="2">12407.8844</dst>
      <dst id="16">30391.5111</dst>
      <dst id="14">5099.4311</dst>
      <dst id="20">5093.1822</dst>
      <dst id="11">2937.8133</dst>
      <dst id="9">835.9644</dst>
      <dst id="17">403794.5422</dst>
      <dst id="21">2022.9422</dst>
      <dst id="15">151.5022</dst>
    </src>
    <src id="5">
      <dst id="12">10335.3778</dst>
      <dst id="13">950.6222</dst>
      <dst id="19">15.4222</dst>
      <dst id="23">27.2889</dst>
      <dst id="8">518.2311</dst>
      <dst id="18">38.3822</dst>
      <dst id="4">447.2000</dst>
      <dst id="1">24669.9556</dst>
      <dst id="3">619.5289</dst>
      <dst id="10">147.7956</dst>
      <dst id="22">26.6844</dst>
      <dst id="2">250.2756</dst>
      <dst id="16">297293.2800</dst>
      <dst id="14">1.1733</dst>
      <dst id="11">3.3067</dst>
      <dst id="9">49068.2489</dst>
      <dst id="17">35245.8311</dst>
      <dst id="21">38.4711</dst>
      <dst id="15">42.4711</dst>
    </src>
    <src id="3">
      <dst id="12">13236.4000</dst>
      <dst id="13">54831.9022</dst>
      <dst id="19">1040.0533</dst>
      <dst id="23">10.0978</dst>
      <dst id="8">1.3867</dst>
      <dst id="18">0.9244</dst>
      <dst id="4">718.0356</dst>
      <dst id="1">43171.8044</dst>
      <dst id="5">306.9600</dst>
      <dst id="3">139.8133</dst>
      <dst id="10">485.0933</dst>
      <dst id="22">3.0044</dst>
      <dst id="7">70811.9911</dst>
      <dst id="2">2943.3422</dst>
      <dst id="16">5875.5467</dst>
      <dst id="14">649.5378</dst>
      <dst id="20">52.7467</dst>
      <dst id="11">369.2267</dst>
      <dst id="9">2026.7556</dst>
      <dst id="17">37202.5867</dst>
      <dst id="21">389.0400</dst>
      <dst id="15">2.5600</dst>
    </src>
    <src id="10">
      <dst id="12">3182.0178</dst>
      <dst id="13">368.8800</dst>
      <dst id="19">5965.8222</dst>
      <dst id="23">1170.5511</dst>
      <dst id="8">64.0978</dst>
      <dst id="18">2816.2400</dst>
      <dst id="1">533.7600</dst>
      <dst id="5">139.1289</dst>
      <dst id="3">730.4889</dst>
      <dst id="22">196.0978</dst>
      <dst id="2">8674.0533</dst>
      <dst id="16">21651.9378</dst>
      <dst id="14">1448.4089</dst>
      <dst id="20">4699.3333</dst>
      <dst id="11">147.8222</dst>
      <dst id="9">2095.3511</dst>
      <dst id="17">26715.7156</dst>
      <dst id="21">5355.3689</dst>
      <dst id="15">173.7511</dst>
    </src>
    <src id="22">
      <dst id="12">16445.3778</dst>
      <dst id="13">12671.5200</dst>
      <dst id="19">72.7378</dst>
      <dst id="23">51.8756</dst>
      <dst id="8">2195.0311</dst>
      <dst id="18">153.2000</dst>
      <dst id="4">475.8400</dst>
      <dst id="1">268.6667</dst>
      <dst id="5">1207.0844</dst>
      <dst id="3">3.2267</dst>
      <dst id="10">250.8178</dst>
      <dst id="7">67.3867</dst>
      <dst id="2">458.2756</dst>
      <dst id="16">65.8400</dst>
      <dst id="14">4.8267</dst>
      <dst id="11">90.9156</dst>
      <dst id="9">1145.2444</dst>
      <dst id="17">1867.5822</dst>
      <dst id="21">214.9422</dst>
    </src>
    <src id="7">
      <dst id="12">5433.0044</dst>
      <dst id="13">5196.1511</dst>
      <dst id="19">88.7733</dst>
      <dst id="23">18.2578</dst>
      <dst id="8">29.0844</dst>
      <dst id="18">4.4267</dst>
      <dst id="4">934.8800</dst>
      <dst id="1">2067.2178</dst>
      <dst id="5">30.3200</dst>
      <dst id="3">31.5733</dst>
      <dst id="10">1460.1422</dst>
      <dst id="22">74.2933</dst>
      <dst id="7">8.9600</dst>
      <dst id="2">5253.1111</dst>
      <dst id="16">152.2578</dst>
      <dst id="14">122.1867</dst>
      <dst id="20">67.0311</dst>
      <dst id="11">920.4178</dst>
      <dst id="9">152.7822</dst>
      <dst id="17">1237.6889</dst>
      <dst id="21">1116.7556</dst>
      <dst id="15">7.4222</dst>
    </src>
    <src id="2">
      <dst id="12">99579.0489</dst>
      <dst id="13">63932.5244</dst>
      <dst id="19">2464.5156</dst>
      <dst id="23">5.0844</dst>
      <dst id="8">111.5556</dst>
      <dst id="18">14448.8622</dst>
      <dst id="4">3348.3733</dst>
      <dst id="1">33770.4800</dst>
      <dst id="5">458.3644</dst>
      <dst id="3">36.6489</dst>
      <dst id="10">2232.5511</dst>
      <dst id="22">224.7378</dst>
      <dst id="7">5958.8533</dst>
      <dst id="2">7305.4667</dst>
      <dst id="6">1.1022</dst>
      <dst id="16">98.7911</dst>
      <dst id="14">625.3511</dst>
      <dst id="20">138.3289</dst>
      <dst id="11">1174.1689</dst>
      <dst id="9">406.7911</dst>
      <dst id="17">12560.6133</dst>
      <dst id="21">1288.6400</dst>
      <dst id="15">13.4756</dst>
    </src>
    <src id="6">
      <dst id="12">420.1067</dst>
      <dst id="13">47.3689</dst>
      <dst id="19">5.4489</dst>
      <dst id="23">0.4267</dst>
      <dst id="4">1.0044</dst>
      <dst id="1">702.0000</dst>
      <dst id="5">0.7111</dst>
      <dst id="3">0.8178</dst>
      <dst id="10">31.3333</dst>
      <dst id="22">4.5778</dst>
      <dst id="7">37.8667</dst>
      <dst id="2">190.5422</dst>
      <dst id="16">15.7689</dst>
      <dst id="20">113.1022</dst>
      <dst id="9">935.1911</dst>
      <dst id="17">21260.3911</dst>
      <dst id="21">1.0311</dst>
      <dst id="15">1.0667</dst>
    </src>
    <src id="16">
      <dst id="12">67002.6667</dst>
      <dst id="13">1631.6800</dst>
      <dst id="19">4934.5600</dst>
      <dst id="23">4.5511</dst>
      <dst id="8">43967.7067</dst>
      <dst id="18">20.8356</dst>
      <dst id="4">138.3911</dst>
      <dst id="1">25121.3422</dst>
      <dst id="5">209514.4622</dst>
      <dst id="3">2607.0222</dst>
      <dst id="10">550.3911</dst>
      <dst id="2">325.9822</dst>
      <dst id="16">14183.8933</dst>
      <dst id="14">49294.0711</dst>
      <dst id="11">10721.1644</dst>
      <dst id="9">142711.6000</dst>
      <dst id="17">2119.3778</dst>
      <dst id="21">93.3333</dst>
    </src>
    <src id="14">
      <dst id="12">639.1644</dst>
      <dst id="13">270.6844</dst>
      <dst id="19">34.7289</dst>
      <dst id="23">0.5244</dst>
      <dst id="18">0.4622</dst>
      <dst id="4">390.7111</dst>
      <dst id="1">1792.2578</dst>
      <dst id="5">66.8622</dst>
      <dst id="3">813.8933</dst>
      <dst id="10">82.2844</dst>
      <dst id="7">189.4044</dst>
      <dst id="2">174.4533</dst>
      <dst id="16">2866.7022</dst>
      <dst id="20">2.5956</dst>
      <dst id="11">13.3333</dst>
      <dst id="9">705.5378</dst>
      <dst id="17">25115.5022</dst>
      <dst id="21">47.6889</dst>
      <dst id="15">2.5067</dst>
    </src>
    <src id="20">
      <dst id="12">425.4489</dst>
      <dst id="13">4386.9689</dst>
      <dst id="19">81.2533</dst>
      <dst id="8">1294.0800</dst>
      <dst id="18">125.6000</dst>
      <dst id="4">210.1600</dst>
      <dst id="1">1403.2711</dst>
      <dst id="5">1344.3733</dst>
      <dst id="3">0.8800</dst>
      <dst id="10">22.6667</dst>
      <dst id="22">13.3333</dst>
      <dst id="7">2298.5156</dst>
      <dst id="2">291.0133</dst>
      <dst id="16">4381.2889</dst>
      <dst id="9">56.7467</dst>
      <dst id="17">1873.6800</dst>
      <dst id="21">24.5956</dst>
    </src>
    <src id="11">
      <dst id="12">17645.8578</dst>
      <dst id="13">921.0222</dst>
      <dst id="19">68.3733</dst>
      <dst id="23">8.7467</dst>
      <dst id="8">13.7244</dst>
      <dst id="18">125.7956</dst>
      <dst id="4">1678.4444</dst>
      <dst id="1">20872.5778</dst>
      <dst id="5">806.8444</dst>
      <dst id="3">854.4178</dst>
      <dst id="10">369.2444</dst>
      <dst id="22">67.3778</dst>
      <dst id="2">1888.6133</dst>
      <dst id="16">8886.3022</dst>
      <dst id="14">79.2178</dst>
      <dst id="20">397.2000</dst>
      <dst id="11">1227.5733</dst>
      <dst id="9">37742.6222</dst>
      <dst id="17">340652.5156</dst>
      <dst id="21">351.3778</dst>
      <dst id="15">74.7200</dst>
    </src>
    <src id="9">
      <dst id="12">14509.6089</dst>
      <dst id="13">1903.2622</dst>
      <dst id="19">29.5822</dst>
      <dst id="23">3.5911</dst>
      <dst id="8">50123.9289</dst>
      <dst id="18">441.4044</dst>
      <dst id="4">426.3289</dst>
      <dst id="1">3752.0444</dst>
      <dst id="5">720.3822</dst>
      <dst id="3">686.7289</dst>
      <dst id="10">784.9600</dst>
      <dst id="22">15.0756</dst>
      <dst id="2">92.0800</dst>
      <dst id="16">511676.8800</dst>
      <dst id="14">54.6311</dst>
      <dst id="11">10.4533</dst>
      <dst id="9">206738.9689</dst>
      <dst id="17">37956.0000</dst>
      <dst id="21">135.0489</dst>
      <dst id="15">15.3156</dst>
    </src>
    <src id="17">
      <dst id="12">44950.6844</dst>
      <dst id="13">29135.4933</dst>
      <dst id="19">12631.4756</dst>
      <dst id="23">35.3956</dst>
      <dst id="8">39.7956</dst>
      <dst id="18">405.0044</dst>
      <dst id="4">8233.0756</dst>
      <dst id="1">16991.9200</dst>
      <dst id="5">118411.9378</dst>
      <dst id="3">2650.8978</dst>
      <dst id="10">4527.0667</dst>
      <dst id="22">622.0622</dst>
      <dst id="7">6045.2889</dst>
      <dst id="2">7387.4578</dst>
      <dst id="16">32817.7067</dst>
      <dst id="14">13703.9111</dst>
      <dst id="20">139.8222</dst>
      <dst id="11">11283.8844</dst>
      <dst id="9">7825.9111</dst>
      <dst id="17">17967.8400</dst>
      <dst id="21">3336.6667</dst>
      <dst id="15">131.7067</dst>
    </src>
    <src id="21">
      <dst id="12">344.3111</dst>
      <dst id="13">1645.7067</dst>
      <dst id="19">38.4622</dst>
      <dst id="23">5.4133</dst>
      <dst id="8">71.6267</dst>
      <dst id="18">7531.0311</dst>
      <dst id="4">438.5067</dst>
      <dst id="1">7240.1600</dst>
      <dst id="5">366.8444</dst>
      <dst id="3">365.5022</dst>
      <dst id="10">228.5778</dst>
      <dst id="22">93.9733</dst>
      <dst id="7">287.1911</dst>
      <dst id="2">2071.8933</dst>
      <dst id="16">6926.0267</dst>
      <dst id="14">26.8889</dst>
      <dst id="20">64.4267</dst>
      <dst id="11">688.1422</dst>
      <dst id="9">1610.0889</dst>
      <dst id="17">17095.8222</dst>
      <dst id="21">302.6667</dst>
      <dst id="15">62.6222</dst>
    </src>
    <src id="15">
      <dst id="12">592.9778</dst>
      <dst id="13">134.1689</dst>
      <dst id="19">43.4044</dst>
      <dst id="23">0.3556</dst>
      <dst id="18">2.9156</dst>
      <dst id="4">69.2089</dst>
      <dst id="1">78.9689</dst>
      <dst id="5">82.2933</dst>
      <dst id="10">157.0133</dst>
      <dst id="2">22.0533</dst>
      <dst id="16">424.5244</dst>
      <dst id="14">85.1556</dst>
      <dst id="11">40.8800</dst>
      <dst id="9">150.7111</dst>
      <dst id="17">466.2756</dst>
      <dst id="21">28.5244</dst>
    </src>
  </IntraTM>
</TrafficMatrixFile>
